amr_crypto/__init__.py
amr_crypto/dlms/__init__.py
amr_crypto/dlms/security.py
amr_crypto-0.0.1.dist-info/DESCRIPTION.rst
amr_crypto-0.0.1.dist-info/LICENSE.txt
amr_crypto-0.0.1.dist-info/METADATA
amr_crypto-0.0.1.dist-info/RECORD
amr_crypto-0.0.1.dist-info/WHEEL
amr_crypto-0.0.1.dist-info/metadata.json
amr_crypto-0.0.1.dist-info/top_level.txt
